README.rst
setup.py
metronomiconic/__init__.py
metronomiconic/main.py
metronomiconic/metronomiconic.py
metronomiconic/version.py
metronomiconic.egg-info/PKG-INFO
metronomiconic.egg-info/SOURCES.txt
metronomiconic.egg-info/dependency_links.txt
metronomiconic.egg-info/entry_points.txt
metronomiconic.egg-info/requires.txt
metronomiconic.egg-info/top_level.txt