Metadata-Version: 1.1
Name: metronomiconic
Version: 0.0.2
Summary: The music learner's metronome with double/half tempo feature
Home-page: http://github.com/trueneu/metronomiconic
Author: trueneu
Author-email: true.neu@gmail.com
License: MIT
Download-URL: https://github.com/trueneu/metronomiconic/archive/v0.0.2.zip
Platform: Posix; MacOS X
Classifier: Development Status :: 3 - Alpha
Classifier: Environment :: Console
Classifier: Environment :: Console :: Curses
Classifier: Intended Audience :: End Users/Desktop
Classifier: Intended Audience :: Other Audience
Classifier: License :: OSI Approved :: MIT License
Classifier: Programming Language :: Python :: 3
Classifier: Programming Language :: Python :: 3 :: Only
Classifier: Programming Language :: Python :: 3.5
Classifier: Topic :: Multimedia :: Sound/Audio
Classifier: Topic :: Multimedia
